metalo/__init__.py
metalo/metalo.py
metalo-0.5.4.dist-info/METADATA
metalo-0.5.4.dist-info/WHEEL
metalo-0.5.4.dist-info/entry_points.txt
metalo-0.5.4.dist-info/licenses/LICENSE
metalo-0.5.4.dist-info/RECORD
