Metadata-Version: 2.1
Name: metalo
Version: 0.5.4
Summary: Metabolic analysis of Logical models extracted from maps
Project-URL: Code, https://gitlab.inria.fr/soliman/metalo
Author-email: Sahar Aghakhani <Sahar.Aghakhani@inria.fr>, Sylvain Soliman <Sylvain.Soliman@inria.fr>
License-Expression: GPL-3.0
License-File: LICENSE
Classifier: Development Status :: 4 - Beta
Classifier: License :: OSI Approved :: GNU General Public License v3 (GPLv3)
Classifier: Operating System :: OS Independent
Classifier: Programming Language :: Python :: 3
Requires-Python: >=3.9
Requires-Dist: casq>=1.3.0
Requires-Dist: cobra>=0.26
Requires-Dist: pandas>=1.5
Requires-Dist: trappist>=0.8.0
Provides-Extra: dev
Requires-Dist: ruff; extra == 'dev'
Provides-Extra: gui
Requires-Dist: gooey>=1.0.8; extra == 'gui'
Requires-Dist: wxpython>=4.2.1; extra == 'gui'
